spanning/__init__.py
spanning-1.0.0.dist-info/METADATA
spanning-1.0.0.dist-info/RECORD
spanning-1.0.0.dist-info/WHEEL
spanning-1.0.0.dist-info/top_level.txt
