Metadata-Version: 2.1
Name: spanning
Version: 1.0.0
Summary: Provides reference-based access over list-like objects
Home-page: https://github.com/Gorea235/python-spanning
Author: Luke (Gorea235)
License: UNKNOWN
Project-URL: Bug Reports, https://github.com/Gorea235/python-spanning/issues
Project-URL: Source, https://github.com/Gorea235/python-spanning
Keywords: list list-like reference large
Platform: UNKNOWN
Classifier: Development Status :: 5 - Production/Stable
Classifier: Intended Audience :: Developers
Classifier: Topic :: Software Development :: Libraries :: Python Modules
Classifier: License :: OSI Approved :: MIT License
Classifier: Programming Language :: Python :: 2
Classifier: Programming Language :: Python :: 2.7
Classifier: Programming Language :: Python :: 3
Classifier: Programming Language :: Python :: 3.6
